{
  "_class": "group",
  "booleanOperation": -1,
  "clippingMaskMode": 0,
  "do_objectID": "0636817E-37FF-4CEF-8AC5-38F780EE8B19",
  "exportOptions": {
    "_class": "exportOptions",
    "exportFormats": [
    ],
    "includedLayerIds": [
    ],
    "layerOptions": 0,
    "shouldTrim": false
  },
  "frame": {
    "_class": "rect",
    "constrainProportions": false,
    "height": 18,
    "width": 128,
    "x": 4,
    "y": 23
  },
  "groupLayout": {
    "_class": "MSImmutableFreeformGroupLayout"
  },
  "hasClickThrough": false,
  "hasClippingMask": false,
  "isFixedToViewport": false,
  "isFlippedHorizontal": false,
  "isFlippedVertical": false,
  "isLocked": false,
  "isVisible": false,
  "layerListExpandedType": 0,
  "layers": [
    {
      "class": "symbolInstance",
      "id": "0A5AB3AC-5750-4CB1-8ADB-49CE26304C08"
    },
    {
      "class": "symbolInstance",
      "id": "2B3883DC-A6B9-468D-9344-AEE440E0A7B2"
    },
    {
      "class": "symbolInstance",
      "id": "EB32A1F5-31DB-4369-B1AD-92CA11396EC5"
    },
    {
      "class": "symbolInstance",
      "id": "243E4206-8D33-4554-9181-EC1F3CDFCC81"
    },
    {
      "class": "symbolInstance",
      "id": "807E7CD0-1E6D-48A8-8979-AC74D71C6709"
    },
    {
      "class": "symbolInstance",
      "id": "1E922BC3-6902-43DC-B113-FD1E7264C6E7"
    },
    {
      "class": "symbolInstance",
      "id": "632AD937-FE31-4294-9936-12DCBD56A41C"
    }
  ],
  "maintainScrollPosition": false,
  "name": "Attributes",
  "nameIsFixed": true,
  "resizingConstraint": 9,
  "resizingType": 0,
  "rotation": 0,
  "shouldBreakMaskChain": false,
  "style": {
    "_class": "style",
    "blur": {
      "_class": "blur",
      "center": "{0.5, 0.5}",
      "isEnabled": false,
      "motionAngle": 0,
      "radius": 10,
      "saturation": 1,
      "type": 0
    },
    "borderOptions": {
      "_class": "borderOptions",
      "dashPattern": [
      ],
      "isEnabled": true,
      "lineCapStyle": 0,
      "lineJoinStyle": 0
    },
    "borders": [
    ],
    "colorControls": {
      "_class": "colorControls",
      "brightness": 0,
      "contrast": 1,
      "hue": 0,
      "isEnabled": true,
      "saturation": 1
    },
    "contextSettings": {
      "_class": "graphicsContextSettings",
      "blendMode": 0,
      "opacity": 1
    },
    "do_objectID": "BA3D9236-05D8-4FDE-8B76-F304A0D27B56",
    "endMarkerType": 0,
    "fills": [
    ],
    "innerShadows": [
    ],
    "miterLimit": 10,
    "shadows": [
    ],
    "startMarkerType": 0,
    "windingRule": 1
  }
}