{
  "_class": "symbolInstance",
  "booleanOperation": -1,
  "clippingMaskMode": 0,
  "do_objectID": "370CEA8F-5488-4FAD-A237-51FB21F87677",
  "exportOptions": {
    "_class": "exportOptions",
    "do_objectID": "88EBCD93-CA27-41D9-8BF7-7E4DE11BC793",
    "exportFormats": [
    ],
    "includedLayerIds": [
    ],
    "layerOptions": 0,
    "shouldTrim": false
  },
  "frame": {
    "_class": "rect",
    "constrainProportions": false,
    "do_objectID": "0EF37239-4369-4FA5-9C12-C8AF5BC68B5A",
    "height": 1,
    "width": 958,
    "x": 0,
    "y": 43
  },
  "hasClippingMask": false,
  "horizontalSpacing": 0,
  "isFixedToViewport": false,
  "isFlippedHorizontal": false,
  "isFlippedVertical": false,
  "isLocked": false,
  "isVisible": true,
  "layerListExpandedType": 0,
  "maintainScrollPosition": false,
  "name": "Controls / Table View / Row / x / Borders / Light / Indent 20pt (Regular Width)",
  "nameIsFixed": false,
  "overrideValues": [
  ],
  "resizingConstraint": 63,
  "resizingType": 0,
  "rotation": 0,
  "scale": 1,
  "shouldBreakMaskChain": false,
  "style": {
    "_class": "style",
    "blur": {
      "_class": "blur",
      "center": "{0.5, 0.5}",
      "do_objectID": "0F8B2B4C-E363-4613-B291-A71C051075B3",
      "isEnabled": false,
      "motionAngle": 0,
      "radius": 10,
      "saturation": 1,
      "type": 0
    },
    "borderOptions": {
      "_class": "borderOptions",
      "dashPattern": [
      ],
      "do_objectID": "6E963334-B3F2-4B76-B0BE-6DF2C4258C17",
      "isEnabled": true,
      "lineCapStyle": 0,
      "lineJoinStyle": 0
    },
    "borders": [
    ],
    "colorControls": {
      "_class": "colorControls",
      "brightness": 0,
      "contrast": 1,
      "do_objectID": "EBB41C35-7F09-46FF-8582-5135840B097D",
      "hue": 0,
      "isEnabled": true,
      "saturation": 1
    },
    "contextSettings": {
      "_class": "graphicsContextSettings",
      "blendMode": 0,
      "do_objectID": "FE31960E-6241-4A3A-9C0A-95D883DC3EAC",
      "opacity": 1
    },
    "do_objectID": "E1A57723-0499-44A7-A739-63EF3A704F9A",
    "endMarkerType": 0,
    "fills": [
    ],
    "innerShadows": [
    ],
    "miterLimit": 10,
    "shadows": [
    ],
    "startMarkerType": 0,
    "windingRule": 1
  },
  "symbolID": "53F43B8D-FF23-4272-A533-4D85196DBC42",
  "verticalSpacing": 0
}