{
  "_class": "symbolMaster",
  "allowsOverrides": true,
  "backgroundColor": {
    "_class": "color",
    "alpha": 1,
    "blue": 1,
    "green": 1,
    "red": 1
  },
  "booleanOperation": -1,
  "changeIdentifier": 3710,
  "clippingMaskMode": 0,
  "do_objectID": "28D6D13D-79A7-403F-92EA-CA25C19542A8",
  "exportOptions": {
    "_class": "exportOptions",
    "exportFormats": [
    ],
    "includedLayerIds": [
    ],
    "layerOptions": 0,
    "shouldTrim": false
  },
  "frame": {
    "_class": "rect",
    "constrainProportions": false,
    "height": 44,
    "width": 958,
    "x": -798,
    "y": 1385
  },
  "groupLayout": {
    "_class": "MSImmutableFreeformGroupLayout"
  },
  "hasBackgroundColor": false,
  "hasClickThrough": true,
  "hasClippingMask": false,
  "horizontalRulerData": {
    "_class": "rulerData",
    "base": 0,
    "guides": [
      513,
      20,
      938,
      885,
      867
    ]
  },
  "includeBackgroundColorInExport": true,
  "includeBackgroundColorInInstance": false,
  "includeInCloudUpload": true,
  "isFixedToViewport": false,
  "isFlippedHorizontal": false,
  "isFlippedVertical": false,
  "isFlowHome": false,
  "isLocked": false,
  "isVisible": true,
  "layerListExpandedType": 2,
  "layers": [
    {
      "class": "rectangle",
      "id": "0C198158-7FA5-404F-B85E-0D655F10B535"
    },
    {
      "class": "text",
      "id": "36EAAEF2-0EBC-46B6-9BF2-0B99FDE8F5AD"
    },
    {
      "class": "text",
      "id": "B0557AAF-69CD-4A16-AA9D-5AFDDA806A18"
    },
    {
      "class": "text",
      "id": "CDBDB14D-85A5-44C4-ADAC-284D95191703"
    },
    {
      "class": "text",
      "id": "064D91A3-C55B-4927-8F1F-309A26261E2D"
    },
    {
      "class": "symbolInstance",
      "id": "96456455-C27B-4C5E-AC6F-31E9B467F885"
    }
  ],
  "maintainScrollPosition": false,
  "name": "Elements/Label/Default/With Textbox /Rounded All",
  "nameIsFixed": true,
  "overrideProperties": [
    {
      "_class": "MSImmutableOverrideProperty",
      "canOverride": true,
      "overrideName": "36EAAEF2-0EBC-46B6-9BF2-0B99FDE8F5AD_stringValue"
    },
    {
      "_class": "MSImmutableOverrideProperty",
      "canOverride": true,
      "overrideName": "6250BD23-D7E5-44EF-8833-9A848A6C2C76_layerStyle"
    },
    {
      "_class": "MSImmutableOverrideProperty",
      "canOverride": true,
      "overrideName": "B0557AAF-69CD-4A16-AA9D-5AFDDA806A18_textStyle"
    },
    {
      "_class": "MSImmutableOverrideProperty",
      "canOverride": true,
      "overrideName": "0C198158-7FA5-404F-B85E-0D655F10B535_layerStyle"
    },
    {
      "_class": "MSImmutableOverrideProperty",
      "canOverride": true,
      "overrideName": "064D91A3-C55B-4927-8F1F-309A26261E2D_stringValue"
    },
    {
      "_class": "MSImmutableOverrideProperty",
      "canOverride": true,
      "overrideName": "B0557AAF-69CD-4A16-AA9D-5AFDDA806A18_stringValue"
    },
    {
      "_class": "MSImmutableOverrideProperty",
      "canOverride": true,
      "overrideName": "36EAAEF2-0EBC-46B6-9BF2-0B99FDE8F5AD_textStyle"
    },
    {
      "_class": "MSImmutableOverrideProperty",
      "canOverride": true,
      "overrideName": "CDBDB14D-85A5-44C4-ADAC-284D95191703_textStyle"
    },
    {
      "_class": "MSImmutableOverrideProperty",
      "canOverride": true,
      "overrideName": "064D91A3-C55B-4927-8F1F-309A26261E2D_textStyle"
    },
    {
      "_class": "MSImmutableOverrideProperty",
      "canOverride": true,
      "overrideName": "CDBDB14D-85A5-44C4-ADAC-284D95191703_stringValue"
    }
  ],
  "presetDictionary": {
  },
  "resizesContent": true,
  "resizingConstraint": 63,
  "resizingType": 0,
  "rotation": 0,
  "shouldBreakMaskChain": true,
  "style": {
    "_class": "style",
    "blur": {
      "_class": "blur",
      "center": "{0.5, 0.5}",
      "isEnabled": false,
      "motionAngle": 0,
      "radius": 10,
      "saturation": 1,
      "type": 0
    },
    "borderOptions": {
      "_class": "borderOptions",
      "dashPattern": [
      ],
      "isEnabled": true,
      "lineCapStyle": 0,
      "lineJoinStyle": 0
    },
    "borders": [
    ],
    "colorControls": {
      "_class": "colorControls",
      "brightness": 0,
      "contrast": 1,
      "hue": 0,
      "isEnabled": true,
      "saturation": 1
    },
    "contextSettings": {
      "_class": "graphicsContextSettings",
      "blendMode": 0,
      "opacity": 1
    },
    "do_objectID": "7762CC29-43C8-476F-B144-85D9ACAD30B0",
    "endMarkerType": 0,
    "fills": [
    ],
    "innerShadows": [
    ],
    "miterLimit": 10,
    "shadows": [
    ],
    "startMarkerType": 0,
    "windingRule": 1
  },
  "symbolID": "E2C1C06A-321E-4DE5-82D8-1A9B35BA3BF0",
  "verticalRulerData": {
    "_class": "rulerData",
    "base": 0,
    "guides": [
    ]
  }
}