{
  "_class": "rectangle",
  "booleanOperation": -1,
  "clippingMaskMode": 0,
  "do_objectID": "DCA16A7D-DA8F-4136-AB3A-DAF736018526",
  "edited": false,
  "exportOptions": {
    "_class": "exportOptions",
    "do_objectID": "79EF012C-63BB-40AA-B48E-7E712FE5C56F",
    "exportFormats": [
    ],
    "includedLayerIds": [
    ],
    "layerOptions": 0,
    "shouldTrim": false
  },
  "fixedRadius": 0,
  "frame": {
    "_class": "rect",
    "constrainProportions": false,
    "do_objectID": "754228B2-2261-4A52-915A-F31BF346FBEC",
    "height": 374.0026595744681,
    "width": 1,
    "x": 186.5013297872341,
    "y": -119.5013297872341
  },
  "hasClippingMask": false,
  "hasConvertedToNewRoundCorners": true,
  "isClosed": true,
  "isFixedToViewport": false,
  "isFlippedHorizontal": false,
  "isFlippedVertical": false,
  "isLocked": false,
  "isVisible": true,
  "layerListExpandedType": 0,
  "maintainScrollPosition": false,
  "name": "Rectangle Copy 7",
  "nameIsFixed": false,
  "needsConvertionToNewRoundCorners": false,
  "pointRadiusBehaviour": 1,
  "points": [
    {
      "_class": "curvePoint",
      "cornerRadius": 0,
      "curveFrom": "{0.24999999999954525, 0}",
      "curveMode": 1,
      "curveTo": "{0.24999999999954525, 0}",
      "hasCurveFrom": false,
      "hasCurveTo": false,
      "point": "{0.24999999999954525, 0}"
    },
    {
      "_class": "curvePoint",
      "cornerRadius": 0,
      "curveFrom": "{0.74999999999954525, 0}",
      "curveMode": 1,
      "curveTo": "{0.74999999999954525, 0}",
      "hasCurveFrom": false,
      "hasCurveTo": false,
      "point": "{0.74999999999954525, 0}"
    },
    {
      "_class": "curvePoint",
      "cornerRadius": 0,
      "curveFrom": "{0.74999999999954536, 1}",
      "curveMode": 1,
      "curveTo": "{0.74999999999954536, 1}",
      "hasCurveFrom": false,
      "hasCurveTo": false,
      "point": "{0.74999999999954536, 1}"
    },
    {
      "_class": "curvePoint",
      "cornerRadius": 0,
      "curveFrom": "{0.24999999999954531, 1}",
      "curveMode": 1,
      "curveTo": "{0.24999999999954531, 1}",
      "hasCurveFrom": false,
      "hasCurveTo": false,
      "point": "{0.24999999999954531, 1}"
    }
  ],
  "resizingConstraint": 63,
  "resizingType": 0,
  "rotation": -90,
  "shouldBreakMaskChain": false,
  "style": {
    "_class": "style",
    "blur": {
      "_class": "blur",
      "center": "{0.5, 0.5}",
      "do_objectID": "D97706DB-84E2-4A19-8EBB-D5D64CCD91DC",
      "isEnabled": false,
      "motionAngle": 0,
      "radius": 10,
      "saturation": 1,
      "type": 0
    },
    "borderOptions": {
      "_class": "borderOptions",
      "dashPattern": [
      ],
      "do_objectID": "F9B1F269-FC98-4B7F-8D2C-EB9AC239090A",
      "isEnabled": true,
      "lineCapStyle": 0,
      "lineJoinStyle": 0
    },
    "borders": [
      {
        "_class": "border",
        "color": {
          "_class": "color",
          "alpha": 1,
          "blue": 0.592,
          "green": 0.592,
          "red": 0.592
        },
        "contextSettings": {
          "_class": "graphicsContextSettings",
          "blendMode": 0,
          "opacity": 1
        },
        "fillType": 0,
        "gradient": {
          "_class": "gradient",
          "elipseLength": 0,
          "from": "{0.5, 0}",
          "gradientType": 0,
          "stops": [
            {
              "_class": "gradientStop",
              "color": {
                "_class": "color",
                "alpha": 1,
                "blue": 1,
                "green": 1,
                "red": 1
              },
              "position": 0
            },
            {
              "_class": "gradientStop",
              "color": {
                "_class": "color",
                "alpha": 1,
                "blue": 0,
                "green": 0,
                "red": 0
              },
              "position": 1
            }
          ],
          "to": "{0.5, 1}"
        },
        "isEnabled": false,
        "position": 0,
        "thickness": 1
      }
    ],
    "colorControls": {
      "_class": "colorControls",
      "brightness": 0,
      "contrast": 1,
      "do_objectID": "F5A481DD-FC76-4197-BADB-F95DB5D262FD",
      "hue": 0,
      "isEnabled": true,
      "saturation": 1
    },
    "contextSettings": {
      "_class": "graphicsContextSettings",
      "blendMode": 0,
      "do_objectID": "C3249EA7-1A04-4D55-B3CF-E7764E8170C7",
      "opacity": 1
    },
    "do_objectID": "1C3A5203-BECE-45D3-93B2-73C365577AFC",
    "endMarkerType": 0,
    "fills": [
      {
        "_class": "fill",
        "color": {
          "_class": "color",
          "alpha": 1,
          "blue": 0.8815104166666666,
          "green": 0.8815104166666666,
          "red": 0.8815104166666666
        },
        "contextSettings": {
          "_class": "graphicsContextSettings",
          "blendMode": 0,
          "opacity": 1
        },
        "fillType": 0,
        "gradient": {
          "_class": "gradient",
          "elipseLength": 0,
          "from": "{0.5, 0}",
          "gradientType": 0,
          "stops": [
            {
              "_class": "gradientStop",
              "color": {
                "_class": "color",
                "alpha": 1,
                "blue": 1,
                "green": 1,
                "red": 1
              },
              "position": 0
            },
            {
              "_class": "gradientStop",
              "color": {
                "_class": "color",
                "alpha": 1,
                "blue": 0,
                "green": 0,
                "red": 0
              },
              "position": 1
            }
          ],
          "to": "{0.5, 1}"
        },
        "isEnabled": true,
        "noiseIndex": 0,
        "noiseIntensity": 0,
        "patternFillType": 1,
        "patternTileScale": 1
      }
    ],
    "innerShadows": [
    ],
    "miterLimit": 10,
    "shadows": [
    ],
    "startMarkerType": 0,
    "windingRule": 1
  }
}