{
  "_class": "symbolInstance",
  "booleanOperation": -1,
  "clippingMaskMode": 0,
  "do_objectID": "7481CC0F-319C-4833-9A81-9570BC53D391",
  "exportOptions": {
    "_class": "exportOptions",
    "exportFormats": [
    ],
    "includedLayerIds": [
    ],
    "layerOptions": 0,
    "shouldTrim": false
  },
  "frame": {
    "_class": "rect",
    "constrainProportions": false,
    "height": 93,
    "width": 74,
    "x": 181,
    "y": 21
  },
  "hasClippingMask": false,
  "horizontalSpacing": 0,
  "isFixedToViewport": false,
  "isFlippedHorizontal": false,
  "isFlippedVertical": false,
  "isLocked": false,
  "isVisible": true,
  "layerListExpandedType": 0,
  "maintainScrollPosition": false,
  "name": "App 3",
  "nameIsFixed": true,
  "overrideValues": [
    {
      "_class": "overrideValue",
      "overrideName": "59A2DA4D-5D6A-48BC-8E3F-78DDB440168E_symbolID",
      "value": ""
    },
    {
      "_class": "overrideValue",
      "overrideName": "7B41E9E6-F498-4F34-A883-A96F5345187F_symbolID",
      "value": "7A4B0BFB-CBF8-4EC7-9EDB-9D91A51FBC79"
    },
    {
      "_class": "overrideValue",
      "overrideName": "4D86F155-D722-414D-9EBA-5E6E04929655_stringValue",
      "value": "Mail"
    }
  ],
  "resizingConstraint": 41,
  "resizingType": 0,
  "rotation": 0,
  "scale": 1,
  "shouldBreakMaskChain": false,
  "style": {
    "_class": "style",
    "blur": {
      "_class": "blur",
      "center": "{0.5, 0.5}",
      "isEnabled": false,
      "motionAngle": 0,
      "radius": 10,
      "saturation": 1,
      "type": 0
    },
    "borderOptions": {
      "_class": "borderOptions",
      "dashPattern": [
      ],
      "isEnabled": true,
      "lineCapStyle": 0,
      "lineJoinStyle": 0
    },
    "borders": [
    ],
    "colorControls": {
      "_class": "colorControls",
      "brightness": 0,
      "contrast": 1,
      "hue": 0,
      "isEnabled": true,
      "saturation": 1
    },
    "contextSettings": {
      "_class": "graphicsContextSettings",
      "blendMode": 0,
      "opacity": 1
    },
    "do_objectID": "06A1C240-C1E8-4266-8AD7-E00966496984",
    "endMarkerType": 0,
    "fills": [
    ],
    "innerShadows": [
    ],
    "miterLimit": 10,
    "shadows": [
    ],
    "startMarkerType": 0,
    "windingRule": 1
  },
  "symbolID": "164B524C-ED41-46A3-A28F-B0C74D4B4A0C",
  "verticalSpacing": 0
}